downloader_exporter-0.5.3.dist-info/METADATA
downloader_exporter-0.5.3.dist-info/WHEEL
downloader_exporter-0.5.3.dist-info/entry_points.txt
downloader_exporter-0.5.3.dist-info/licenses/LICENSE
downloader_exporter/__init__.py
downloader_exporter-0.5.3.dist-info/RECORD
