Metadata-Version: 2.1
Name: downloader-exporter
Version: 0.5.3
Summary: Prometheus exporter for torrent downloader like qbittorrent/transmission/deluge
Keywords: prometheus,qbittorrent,transmission,deluge
Author-Email: Lei Shi <me@leishi.io>
License: MIT
Project-URL: Homepage, https://github.com/leishi1313/downloader-exporter
Project-URL: Downloads, https://github.com/leishi1313/downloader-exporter/releases/latest
Requires-Python: >=3.9
Requires-Dist: attrdict==2.0.1
Requires-Dist: deluge-client==1.10.2
Requires-Dist: loguru==0.7.3
Requires-Dist: prometheus_client==0.21.1
Requires-Dist: pyyaml==6.0.2
Requires-Dist: qbittorrent-api==2024.12.71
Requires-Dist: transmission-rpc==7.0.11
